Metadata-Version: 2.1
Name: nubcrypt
Version: 0.0.1
Summary: Data encryption
Home-page: https://github.com/nubcakee/nubcrypt
Author: Anggi Kharisma Putra
Author-email: anggikharismaputra@gmail.com
License: MIT
Keywords: encryption,data-encryption,cryptography
Platform: UNKNOWN
